azure/ai/textanalytics/__init__.py
azure/ai/textanalytics/_base_client.py
azure/ai/textanalytics/_check.py
azure/ai/textanalytics/_dict_mixin.py
azure/ai/textanalytics/_lro.py
azure/ai/textanalytics/_models.py
azure/ai/textanalytics/_policies.py
azure/ai/textanalytics/_request_handlers.py
azure/ai/textanalytics/_response_handlers.py
azure/ai/textanalytics/_text_analytics_client.py
azure/ai/textanalytics/_user_agent.py
azure/ai/textanalytics/_validate.py
azure/ai/textanalytics/_version.py
azure/ai/textanalytics/py.typed
azure/ai/textanalytics/_generated/__init__.py
azure/ai/textanalytics/_generated/_configuration.py
azure/ai/textanalytics/_generated/_operations_mixin.py
azure/ai/textanalytics/_generated/_serialization.py
azure/ai/textanalytics/_generated/_text_analytics_client.py
azure/ai/textanalytics/_generated/_version.py
azure/ai/textanalytics/_generated/models.py
azure/ai/textanalytics/_generated/aio/__init__.py
azure/ai/textanalytics/_generated/aio/_configuration.py
azure/ai/textanalytics/_generated/aio/_operations_mixin.py
azure/ai/textanalytics/_generated/aio/_text_analytics_client.py
azure/ai/textanalytics/_generated/v2022_05_01/__init__.py
azure/ai/textanalytics/_generated/v2022_05_01/_configuration.py
azure/ai/textanalytics/_generated/v2022_05_01/_patch.py
azure/ai/textanalytics/_generated/v2022_05_01/_text_analytics_client.py
azure/ai/textanalytics/_generated/v2022_05_01/_vendor.py
azure/ai/textanalytics/_generated/v2022_05_01/aio/__init__.py
azure/ai/textanalytics/_generated/v2022_05_01/aio/_configuration.py
azure/ai/textanalytics/_generated/v2022_05_01/aio/_patch.py
azure/ai/textanalytics/_generated/v2022_05_01/aio/_text_analytics_client.py
azure/ai/textanalytics/_generated/v2022_05_01/aio/_vendor.py
azure/ai/textanalytics/_generated/v2022_05_01/aio/operations/__init__.py
azure/ai/textanalytics/_generated/v2022_05_01/aio/operations/_patch.py
azure/ai/textanalytics/_generated/v2022_05_01/aio/operations/_text_analytics_client_operations.py
azure_ai_textanalytics-5.3.0.dist-info/LICENSE
azure_ai_textanalytics-5.3.0.dist-info/METADATA
azure_ai_textanalytics-5.3.0.dist-info/WHEEL
azure_ai_textanalytics-5.3.0.dist-info/top_level.txt
azure_ai_textanalytics-5.3.0.dist-info/RECORD
